python_libxdo-0.1.1a0.dist-info/RECORD
python_libxdo-0.1.1a0.dist-info/DESCRIPTION.rst
python_libxdo-0.1.1a0.dist-info/top_level.txt
python_libxdo-0.1.1a0.dist-info/METADATA
python_libxdo-0.1.1a0.dist-info/metadata.json
python_libxdo-0.1.1a0.dist-info/WHEEL
xdo/__init__.py
xdo/xdo.py
