Metadata-Version: 1.1
Name: python-libxdo
Version: 0.1.1a0
Summary: Python bindings for libxdo
Home-page: UNKNOWN
Author: Samuele Santi
Author-email: samuele@samuelesanti.com
License: BSD License
Platform: UNKNOWN
Classifier: License :: OSI Approved :: BSD License
Classifier: Development Status :: 1 - Planning
Classifier: Programming Language :: Python :: 2
Classifier: Programming Language :: Python :: 2.7
Classifier: Programming Language :: Python :: Implementation :: CPython
